{
    "Parameters": {
        "XPExponent": 1.35,
        "CombatChance": 0.45,
        "DeathChance": 0.08,
        "RepairCostPct": 0.05,
        "RespecChanceCombat": 0.03,
        "RespecBaseCost": 100,
        "RespecLevelMult": 10,
        "VendorTaxPct": 0.1,
        "ZoneTier": 1,
        "BaseXP_Combat": 12,
        "BaseXP_NonCombat": 10,
        "SkillDiff_TierMult": 5,
        "SkillDiff_StDev": 2,
        "TimePerStep_Min": 3,
        "DeathSeverity": 0.5,
        "RepairCostPerZone": 0.4,
        "StepCount": 20,
        "RunID": 1,
        "Seed": 1,
        "BaseRecommendedGear": 100,
        "GearGrowthPerZone": 1.08,
        "ZoneScale": 7,
        "GearStatScaling": 15
    },
    "GearQualityWeights": {
        "Tiers": {
            "T1": {
                "Common": 0.7,
                "Rare": 0.22,
                "Epic": 0.07,
                "Legendary": 0.01
            },
            "T2": {
                "Common": 0.5,
                "Rare": 0.35,
                "Epic": 0.1,
                "Legendary": 0.05
            },
            "T3": {
                "Common": 0.2,
                "Rare": 0.4,
                "Epic": 0.3,
                "Legendary": 0.2
            },
            "T4": {
                "Common": 0.03,
                "Rare": 0.07,
                "Epic": 0.4,
                "Legendary": 0.5
            }
        },
        "Thresholds": {
            "T1": {
                "Common": 0.4,
                "Rare": 0.7,
                "Epic": 0.9,
                "Legendary": 1
            },
            "T2": {
                "Common": 0.55,
                "Rare": 0.85,
                "Epic": 0.97,
                "Legendary": 1
            },
            "T3": {
                "Common": 0.4,
                "Rare": 0.75,
                "Epic": 0.95,
                "Legendary": 1
            },
            "T4": {
                "Common": 0.25,
                "Rare": 0.65,
                "Epic": 0.92,
                "Legendary": 1
            }
        }
    },
    "DropThresholds": {
        "Weapon": 0.2,
        "Chest": 0.2,
        "Helm": 0.2,
        "Legs": 0.2,
        "Accessory": 0.2
    },
    "ScoreWeights": {
        "Common": 0.9,
        "Rare": 1.0,
        "Epic": 1.2,
        "Legendary": 1.4,
        "Zone": 0.6
    }
}